StegoSaurusPy/__init__.py
StegoSaurusPy/attach.py
StegoSaurusPy/detach.py
stegosauruspy-1.1.dist-info/METADATA
stegosauruspy-1.1.dist-info/WHEEL
stegosauruspy-1.1.dist-info/licenses/LICENSE.txt
stegosauruspy-1.1.dist-info/RECORD
