Metadata-Version: 2.1
Name: StegoSaurusPy
Version: 1.1
Summary: Using steganography to hide binary data in other files
Author: reddust9
License:                     GNU GENERAL PUBLIC LICENSE
Classifier: Operating System :: OS Independent
Classifier: Programming Language :: Python :: 3
Requires-Python: >=3.7
